.gitignore
DEMO.md
README.md
my_test.py
requirements.txt
setup.py
.idea/.gitignore
.idea/cassandra.iml
.idea/csv-plugin.xml
.idea/misc.xml
.idea/modules.xml
.idea/vcs.xml
.idea/inspectionProfiles/Project_Default.xml
.idea/inspectionProfiles/profiles_settings.xml
src/__init__.py
src/cassandra/__init__.py
src/cassandra/budgetAllocator/__init__.py
src/cassandra/budgetAllocator/budget_allocator.py
src/cassandra/budgetAllocator/plot.py
src/cassandra/budgetAllocator/utils.py
src/cassandra/data/__init__.py
src/cassandra/data/dataAnalysis/__init__.py
src/cassandra/data/dataAnalysis/correlation.py
src/cassandra/data/dataAnalysis/plot.py
src/cassandra/data/dataAnalysis/exploration/__init__.py
src/cassandra/data/dataAnalysis/exploration/exploration.py
src/cassandra/data/dataAnalysis/exploration/utils.py
src/cassandra/data/dataAnalysis/outliers/__init__.py
src/cassandra/data/dataAnalysis/outliers/outliers.py
src/cassandra/data/dataAnalysis/outliers/plot.py
src/cassandra/data/dataProcessing/__init__.py
src/cassandra/data/dataProcessing/clean_and_format.py
src/cassandra/data/dataProcessing/prophet.py
src/cassandra/data/featureSelection/__init__.py
src/cassandra/data/featureSelection/feature_selection.py
src/cassandra/data/featureSelection/mlm.py
src/cassandra/data/featureSelection/multicollinearity.py
src/cassandra/data/featureSelection/ols.py
src/cassandra/data/trasformations/__init__.py
src/cassandra/data/trasformations/trasformations.py
src/cassandra/helper/__init__.py
src/cassandra/helper/clean_and_format.txt
src/cassandra/helper/functions.py
src/cassandra/helper/import.txt
src/cassandra/helper/nevergrad.txt
src/cassandra/helper/other.txt
src/cassandra/helper/pivot.txt
src/cassandra/model/__init__.py
src/cassandra/model/bayesianRidge.py
src/cassandra/model/deepLearning.py
src/cassandra/model/linear.py
src/cassandra/model/logLinear.py
src/cassandra/model/logLog.py
src/cassandra/model/logistic.py
src/cassandra/model/mlpRegressor.py
src/cassandra/model/nestedModel.py
src/cassandra_mmm.egg-info/PKG-INFO
src/cassandra_mmm.egg-info/SOURCES.txt
src/cassandra_mmm.egg-info/dependency_links.txt
src/cassandra_mmm.egg-info/top_level.txt