Metadata-Version: 2.1
Name: cassandra-mmm
Version: 1.1.8
Summary: Cassandra library
Home-page: https://github.com/Tsurty/cassandra
Author: Cassandra
License: MIT
Platform: UNKNOWN
